{"matched": 3800, "page_results": [{"object": {"main_id": "M 25", "main_name": "M 25", "ids": ["M 25", "IC 4725", "CL MELOTTE 204"], "names": [], "family": "deep_sky_object", "types": ["opcl", "stcl", "deep_sky_object", "str", "stass", "uvsrc"], "url": "https://telescopius.com/deep-sky-objects/m-25/open-cluster/star/stellar-association", "main_image_url": "https://telescopius.com/img/dsos/6962fb38d941a0170cc4702b6dbc26d9_fullhd.webp", "thumbnail_url": "https://telescopius.com/img/dsos/6962fb38d941a0170cc4702b6dbc26d9_thumbnail.webp", "alt_ids": ["MESSIER 25", "MEL 204", "MELOTTE 204"], "ra": 18.529139, "dec": -19.113889, "con": "SGR", "con_name": "Sagittarius", "visual_mag": 4.6, "major_axis": 1560, "redshift": 3.4e-05, "subr": 20.3}, "tonight_times": {"rise": "20:04", "transit": "00:40", "set": "05:27"}, "transit_observation": {"ra": 18.529139, "dec": -19.113889, "dist_au": 0, "alt": 27.1, "az": 179.46, "mag": 4.6, "con": "SGR"}, "tonight_visibility": {"max_altitude": 27, "max_altitude_hour": "00:40", "windows": [{"start": "23:37", "end": "04:00", "imaging_time_hours": 4.38, "moon_illumination_percent": 0.01, "moon_distance_deg": 156.3}]}}]}