{"matched": 1, "page_results": [{"object": {"main_id": "NGC 2403", "main_name": "NGC 2403", "ids": ["NGC 2403", "MCG +11-10-007", "PGC 21396", "UGC 3918", "Z 310-3", "Z 309-40", "Z 0732.0+6543", "IRAS 07320+6543", "IRAS 07321+6543", "IRAS F07320+6543", "C 7", "MCG +11-10-07", "MCG +11-10-7"], "names": [], "family": "deep_sky_object", "types": ["sgx", "gxy", "deep_sky_object", "bgx", "agn", "str", "irsrc", "xrsrc"], "url": "https://telescopius.com/deep-sky-objects/ngc-2403/spiral-galaxy/barred-spiral-galaxy/active-galaxy-nucleus", "main_image_url": "https://telescopius.com/img/dsos/9014b3bb01ab42fd4758947feb53c405_fullhd.webp", "thumbnail_url": "https://telescopius.com/img/dsos/9014b3bb01ab42fd4758947feb53c405_thumbnail.webp", "alt_ids": ["CGCG 310-3", "LEDA 21396", "CPG 21396", "UGCG 3918", "ZWG 310-3", "CALDWELL 7"], "ra": 7.614261, "dec": 65.602681, "con": "CAM", "con_name": "Camelopardalis", "visual_mag": 8.4, "photo_mag": 8.8, "major_axis": 1282, "minor_axis": 643, "pa_east": 126, "redshift": 0.000434, "subr": 22.9, "morph_class": "SAcd"}, "tonight_times": {"rise": "", "transit": "13:50", "set": ""}, "transit_observation": {"ra": 7.614261, "dec": 65.602681, "dist_au": 0, "alt": 68.18, "az": 0.56, "mag": 8.4, "con": "CAM"}, "tonight_visibility": {"max_altitude": 68, "max_altitude_hour": "13:50", "windows": [{"start": "23:39", "end": "03:58", "imaging_time_hours": 4.33, "moon_illumination_percent": 0, "moon_distance_deg": 40.6}]}}]}