{"matched": 1599, "page_results": [{"object": {"main_id": "M 109", "main_name": "M 109", "ids": ["M 109", "NGC 3992", "MCG +09-20-044", "PGC 37617", "UGC 6937", "Z 269-23", "Z 1155.0+5339", "IRAS 11549+5339", "IRAS 11550+5339", "MCG +09-20-44"], "names": [], "family": "deep_sky_object", "types": ["sgx", "gxy", "deep_sky_object", "bgx", "str", "irsrc", "optsrc"], "url": "https://telescopius.com/deep-sky-objects/m-109/spiral-galaxy/barred-spiral-galaxy/galaxy", "main_image_url": "https://telescopius.com/img/dsos/147279a7f040ee215330b8a322573e9e_fullhd.webp", "thumbnail_url": "https://telescopius.com/img/dsos/147279a7f040ee215330b8a322573e9e_thumbnail.webp", "alt_ids": ["MESSIER 109", "CGCG 269-23", "LEDA 37617", "CPG 37617", "UGCG 6937", "ZWG 269-23"], "ra": 11.95999, "dec": 53.374724, "con": "UMA", "con_name": "Ursa Major", "visual_mag": 10.6, "photo_mag": 10.9, "major_axis": 450, "minor_axis": 264, "pa_east": 78, "redshift": 0.003502, "subr": 23, "morph_class": "SB"}, "tonight_times": {"rise": "", "transit": "18:06", "set": ""}, "transit_observation": {"ra": 11.95999, "dec": 53.374724, "dist_au": 0, "alt": 80.41, "az": 1.81, "mag": 10.6, "con": "UMA"}, "tonight_visibility": {"max_altitude": 80, "max_altitude_hour": "18:06", "windows": [{"start": "23:37", "end": "04:00", "imaging_time_hours": 4.38, "moon_illumination_percent": 0.01, "moon_distance_deg": 52.9}]}}]}