{"matched": 697, "page_results": [{"object": {"main_id": "M 88", "main_name": "M 88", "ids": ["M 88", "NGC 4501", "MCG +03-32-059", "PGC 41517", "UGC 7675", "Z 99-76", "Z 1229.4+1442", "IRAS 12294+1441", "IRAS F12294+1441", "MCG +03-32-59"], "names": [], "family": "deep_sky_object", "types": ["sgx", "gxy", "deep_sky_object", "sf2gx", "sfgx", "agn", "h1r", "radsrc", "str", "irsrc", "xrsrc", "gamsrc"], "url": "https://telescopius.com/deep-sky-objects/m-88/spiral-galaxy/seyfert-2-galaxy/active-galaxy-nucleus", "main_image_url": "https://telescopius.com/img/dsos/a895fe2bad3165aa6859a3bc7e5f0e61_fullhd.webp", "thumbnail_url": "https://telescopius.com/img/dsos/a895fe2bad3165aa6859a3bc7e5f0e61_thumbnail.webp", "alt_ids": ["MESSIER 88", "CGCG 99-76", "LEDA 41517", "CPG 41517", "UGCG 7675", "ZWG 99-76"], "ra": 12.533098, "dec": 14.420319, "con": "COM", "con_name": "Coma Berenices", "visual_mag": 10.4, "photo_mag": 14.3, "major_axis": 408, "minor_axis": 222, "pa_east": 138, "redshift": 0.007641, "subr": 25.7, "morph_class": "SA"}, "tonight_times": {"rise": "11:46", "transit": "18:41", "set": "01:41"}, "transit_observation": {"ra": 12.533098, "dec": 14.420319, "dist_au": 0, "alt": 60.63, "az": 179.01, "mag": 10.4, "con": "COM"}, "tonight_visibility": {"max_altitude": 61, "max_altitude_hour": "18:41", "windows": [{"start": "23:37", "end": "01:41", "imaging_time_hours": 2.07, "moon_illumination_percent": 0.01, "moon_distance_deg": 62.6}]}}]}