{"matched": 3081, "page_results": [{"object": {"main_id": "M 42", "main_name": "Orion Nebula", "ids": ["M 42", "NGC 1976", "LBN 974", "LBN 209.13-19.35", "3C 145"], "names": ["Orion Nebula"], "family": "deep_sky_object", "types": ["h2r", "eneb", "dineb", "neb", "ism", "deep_sky_object", "opcl", "stcl", "radsrc", "xrsrc"], "url": "https://telescopius.com/deep-sky-objects/m-42/orion-nebula/h2-region/open-cluster/star-cluster", "main_image_url": "https://telescopius.com/img/dsos/03b7b043f17dd6e3475ef2193e6c2b0b_fullhd.webp", "thumbnail_url": "https://telescopius.com/img/dsos/03b7b043f17dd6e3475ef2193e6c2b0b_thumbnail.webp", "alt_ids": ["MESSIER 42"], "ra": 5.588056, "dec": -5.39, "con": "ORI", "con_name": "Orion", "visual_mag": 4, "major_axis": 5400, "minor_axis": 3600, "pa_east": 90, "redshift": 9.3e-05, "subr": 22}, "tonight_times": {"rise": "06:07", "transit": "11:41", "set": "17:27"}, "transit_observation": {"ra": 5.588056, "dec": -5.39, "dist_au": 0, "alt": 40.82, "az": 179.34, "mag": 4, "con": "ORI"}, "tonight_visibility": {"max_altitude": 41, "max_altitude_hour": "11:41", "windows": []}}]}